{
	"name": "Член. Вздрочнуть в одиночестве.",
	"description": "Видимо пора вернуться к той что никогда не оставит без ласки - к руке.",
	"usage": "other",
	"category": "Erp",
	"distance_allowed": 0,
	"message": [
		"%USER% хватает свой член подрачивая.",
		"%USER% активно пыхтит и трогает себя.",
		"%USER% насилует свой кулак.",
		"%USER% сжимает пенис так что вены на руке набухают и дрочит себе."
	],
	"sound_use": 1,
	"sound_range": 3,
	"interaction_requires": [
		"self_hand"
	],
	"target_required_parts": [
		"penis"
	],
	"color": "purple",
	"user_arousal": 7,
	"user_pleasure": 7,
	"lewd": 1,
	"sound_possible": [
		"modular_skyrat/modules/modular_items/lewd_items/sounds/bang1.ogg",
		"modular_skyrat/modules/modular_items/lewd_items/sounds/bang2.ogg",
		"modular_skyrat/modules/modular_items/lewd_items/sounds/foot_wet2.ogg",
		"modular_skyrat/modules/modular_items/lewd_items/sounds/foot_wet3.ogg"
	]
}
